Workbook

Sheet Executive Dashboard
A1: LeadPulse Growth Analytics Dashboard
A3: 30-Day Multi-Channel Growth Marketing Forecast
A4: All figures are illustrative planning assumptions, not actual campaign results.
A6: Total Marketing Budget | E6: Total Leads | I6: Qualified Leads
A7: ='Input Assumptions'!B6 -> 150000 | E7: ='Input Assumptions'!F30 -> 760 | I7: ='Input Assumptions'!G30 -> 304
A11: Customers Acquired | E11: Customer Acquisition Cost (CAC) | I11: Customer Lifetime Value (LTV)
A12: ='ROI & Scenario Planning'!B6 -> 60.8 | E12: ='ROI & Scenario Planning'!B7 -> 2467.1053 | I12: ='ROI & Scenario Planning'!B14 -> 43750
A16: LTV:CAC Ratio | E16: Estimated Revenue | I16: Estimated ROI
A17: ='ROI & Scenario Planning'!B15 -> 17.733333 | E17: ='ROI & Scenario Planning'!B9 -> 152000 | I17: ='ROI & Scenario Planning'!B13 -> -0.29066667

Sheet Input Assumptions
A1: INPUT ASSUMPTIONS
A2: Editable planning inputs — yellow cells drive every calculation in this workbook. All figures are Illustrative Forecast / Planning Assumptions.
A4: Campaign Assumptions
A5: Campaign Duration (Days) | B5: 30
A6: Total Marketing Budget (PKR) | B6: 150000
A7: Currency | B7: PKR
A8: Monthly Subscription Price (PKR) | B8: 2500
A9: Monthly Churn Rate | B9: 0.04
A10: Average Customer Lifespan (Months) | B10: =1/B9 -> 25
A11: Gross Margin | B11: 0.7
A12: Landing Page Conversion Rate (Clicks to Leads) | B12: 0.1
A13: Lead Qualification Rate (Leads to Qualified) | B13: 0.4
A14: Trial/Demo-to-Paid Conversion Rate | B14: 0.2
A16: Channel Budgets
A17: Channel | B17: Budget % | C17: Budget (PKR)
A18: Google Ads | B18: 0.4 | C18: =B18*$B$6 -> 60000
A19: LinkedIn Ads | B19: 0.35 | C19: =B19*$B$6 -> 52500
A20: Organic Social Media | B20: 0.15 | C20: =B20*$B$6 -> 22500
A21: Email Marketing | B21: 0.1 | C21: =B21*$B$6 -> 15000
A22: Total | B22: =SUM(B18:B21) -> 1 | C22: =SUM(C18:C21) -> 150000
A24: Channel Forecast Inputs
A25: Channel | B25: Budget (PKR) | C25: Impressions | D25: CTR | E25: Clicks | F25: Leads | G25: Qualified Leads | H25: Customers
A26: Google Ads | B26: =C18 -> 60000 | C26: 150000 | D26: 0.03 | E26: =C26*D26 -> 4500 | F26: =E26*$B$12 -> 450 | G26: =F26*$B$13 -> 180 | H26: =G26*$B$14 -> 36
A27: LinkedIn Ads | B27: =C19 -> 52500 | C27: 100000 | D27: 0.006 | E27: =C27*D27 -> 600 | F27: =E27*$B$12 -> 60 | G27: =F27*$B$13 -> 24 | H27: =G27*$B$14 -> 4.8
A28: Organic Social Media | B28: =C20 -> 22500 | C28: 200000 | D28: 0.01 | E28: =C28*D28 -> 2000 | F28: =E28*$B$12 -> 200 | G28: =F28*$B$13 -> 80 | H28: =G28*$B$14 -> 16
A29: Email Marketing | B29: =C21 -> 15000 | C29: 5000 | D29: 0.1 | E29: =C29*D29 -> 500 | F29: =E29*$B$12 -> 50 | G29: =F29*$B$13 -> 20 | H29: =G29*$B$14 -> 4
A30: Total | B30: =SUM(B26:B29) -> 150000 | C30: =SUM(C26:C29) -> 455000 | D30: =IFERROR(E30/C30,0) -> 0.016703297 | E30: =SUM(E26:E29) -> 7600 | F30: =SUM(F26:F29) -> 760 | G30: =SUM(G26:G29) -> 304 | H30: =SUM(H26:H29) -> 60.8
A32: Yellow cells (Impressions, CTR, and top assumptions) are editable inputs. Changing them automatically updates every sheet in this workbook.
A33: All figures are Illustrative Forecast / Planning Assumptions for internship purposes — not actual campaign data.

Sheet Funnel Forecast
A1: FUNNEL FORECAST
A2: Illustrative Forecast / Planning Assumptions — 30-Day Multi-Channel Campaign
A4: Funnel Stage | B4: Value | C4: Conversion Rate from Previous Stage | D4: Notes
A5: Impressions | B5: ='Input Assumptions'!C30 -> 455000 | C5: - | D5: Total paid + organic + email impressions/sends
A6: Clicks | B6: ='Input Assumptions'!E30 -> 7600 | C6: =IFERROR(B6/B5,0) -> 0.016703297 | D6: Blended click-through rate across channels
A7: Website Visits | B7: =B6 -> 7600 | C7: =IFERROR(B7/B6,0) -> 1 | D7: Assumes each click lands on the site (1:1)
A8: Leads | B8: ='Input Assumptions'!F30 -> 760 | C8: =IFERROR(B8/B7,0) -> 0.1 | D8: Visits converting via landing page form
A9: Qualified Leads | B9: ='Input Assumptions'!G30 -> 304 | C9: =IFERROR(B9/B8,0) -> 0.4 | D9: Leads meeting ICP/qualification criteria
A10: Trial/Demo Signups | B10: =B9 -> 304 | C10: =IFERROR(B10/B9,0) -> 1 | D10: Assumes qualified leads proceed to a trial/demo
A11: Paying Customers | B11: ='Input Assumptions'!H30 -> 60.8 | C11: =IFERROR(B11/B10,0) -> 0.2 | D11: Trial/demo signups converting to paid
A13: Where the Biggest Drop-Off Occurs
A14: The largest drop-off in the funnel happens between Impressions and Clicks — the blended click-through rate across Google, LinkedIn, Organic Social, and Email is well under 5%, consistent with typical multi-channel digital campaigns. Every later stage (Leads → Qualified → Trial → Paying Customer) narrows the funnel further but at a much lower rate. This suggests creative and targeting refinements to raise CTR would have the largest leverage on total customers acquired.

Sheet CAC & LTV Analysis
A1: CAC & LTV ANALYSIS
A2: Illustrative Forecast / Planning Assumptions
A4: Customer Acquisition Cost (CAC)
A5: CAC = Total Marketing Cost ÷ Number of New Customers
A6: Channel | B6: Budget (PKR) | C6: Leads | D6: Customers | E6: CAC (PKR)
A7: Google Ads | B7: ='Input Assumptions'!B26 -> 60000 | C7: ='Input Assumptions'!F26 -> 450 | D7: ='Input Assumptions'!H26 -> 36 | E7: =IFERROR(B7/D7,0) -> 1666.6667
A8: LinkedIn Ads | B8: ='Input Assumptions'!B27 -> 52500 | C8: ='Input Assumptions'!F27 -> 60 | D8: ='Input Assumptions'!H27 -> 4.8 | E8: =IFERROR(B8/D8,0) -> 10937.5
A9: Organic Social Media | B9: ='Input Assumptions'!B28 -> 22500 | C9: ='Input Assumptions'!F28 -> 200 | D9: ='Input Assumptions'!H28 -> 16 | E9: =IFERROR(B9/D9,0) -> 1406.25
A10: Email Marketing | B10: ='Input Assumptions'!B29 -> 15000 | C10: ='Input Assumptions'!F29 -> 50 | D10: ='Input Assumptions'!H29 -> 4 | E10: =IFERROR(B10/D10,0) -> 3750
A11: Total / Blended CAC | B11: =SUM(B7:B10) -> 150000 | C11: =SUM(C7:C10) -> 760 | D11: =SUM(D7:D10) -> 60.8 | E11: =IFERROR(B11/D11,0) -> 2467.1053
A13: Customer Lifetime Value (LTV)
A14: LTV = Monthly Revenue Per Customer × Customer Lifespan × Gross Margin
A15: Monthly Revenue Per Customer (PKR) | B15: ='Input Assumptions'!B8 -> 2500
A16: Monthly Churn Rate | B16: ='Input Assumptions'!B9 -> 0.04
A17: Average Customer Lifespan (Months) | B17: ='Input Assumptions'!B10 -> 25
A18: Gross Margin | B18: ='Input Assumptions'!B11 -> 0.7
A19: Customer Lifetime Value (LTV) (PKR) | B19: =B15*B17*B18 -> 43750
A21: LTV Sensitivity — Churn Rate
A22: Churn Rate | B22: Lifespan (Months) | C22: LTV (PKR)
A23: 0.02 | B23: =1/A23 -> 50 | C23: =$B$15*B23*$B$18 -> 87500
A24: 0.03 | B24: =1/A24 -> 33.333333 | C24: =$B$15*B24*$B$18 -> 58333.333
A25: 0.04 | B25: =1/A25 -> 25 | C25: =$B$15*B25*$B$18 -> 43750
A26: 0.05 | B26: =1/A26 -> 20 | C26: =$B$15*B26*$B$18 -> 35000
A27: 0.06 | B27: =1/A27 -> 16.666667 | C27: =$B$15*B27*$B$18 -> 29166.667
A29: Sensitivity table shows how LTV changes if monthly churn differs from the base assumption of 4% (row 16). Lower churn materially increases LTV and the LTV:CAC ratio.
A32: Chart Data
A33: Blended CAC | B33: =E11 -> 2467.1053
A34: LTV | B34: =B19 -> 43750

Sheet ROI & Scenario Planning
A1: ROI & SCENARIO PLANNING
A2: Illustrative Forecast / Planning Assumptions
A4: Base Case Forecast (30 Days)
A5: Marketing Cost (PKR) | B5: ='Input Assumptions'!B6 -> 150000
A6: Customers Acquired | B6: ='CAC & LTV Analysis'!D11 -> 60.8
A7: CAC (PKR) | B7: ='CAC & LTV Analysis'!E11 -> 2467.1053
A8: Monthly Revenue Per Customer (PKR) | B8: ='Input Assumptions'!B8 -> 2500
A9: Monthly Revenue (PKR) | B9: =B6*B8 -> 152000
A10: Gross Margin | B10: ='Input Assumptions'!B11 -> 0.7
A11: Gross Profit (PKR) | B11: =B9*B10 -> 106400
A12: Estimated Profit After Marketing Cost (PKR) | B12: =B11-B5 -> -43600
A13: ROI (%) | B13: =IFERROR((B11-B5)/B5,0) -> -0.29066667
A14: LTV (PKR) | B14: ='CAC & LTV Analysis'!B19 -> 43750
A15: LTV:CAC Ratio | B15: =IFERROR(B14/B7,0) -> 17.733333
A16: Contribution Margin Per Customer (PKR) | B16: =B8*B10 -> 1750
A17: Break-Even Customers (Month 1) | B17: =IFERROR(B5/B16,0) -> 85.714286
A18: Month-1 ROI is expected to be negative: marketing cost is paid up front while subscription revenue is recovered gradually over the customer's full lifespan. The LTV:CAC ratio (row 15) is the better indicator of long-run profitability than the single-month ROI figure above.
A21: Scenario Comparison
A22: Metric | B22: Conservative | C22: Base | D22: Optimistic
A23: Scenario Multiplier (applied to Leads/Customers) | B23: 0.7 | C23: 1 | D23: 1.3
A24: Leads | B24: ='Input Assumptions'!$F$30*B23 -> 532 | C24: ='Input Assumptions'!$F$30*C23 -> 760 | D24: ='Input Assumptions'!$F$30*D23 -> 988
A25: Customers | B25: ='Input Assumptions'!$H$30*B23 -> 42.56 | C25: ='Input Assumptions'!$H$30*C23 -> 60.8 | D25: ='Input Assumptions'!$H$30*D23 -> 79.04
A26: CAC (PKR) | B26: =IFERROR($B$5/B25,0) -> 3524.4361 | C26: =IFERROR($B$5/C25,0) -> 2467.1053 | D26: =IFERROR($B$5/D25,0) -> 1897.7733
A27: LTV (PKR) | B27: =$B$14 -> 43750 | C27: =$B$14 -> 43750 | D27: =$B$14 -> 43750
A28: Revenue (PKR) | B28: =B25*$B$8 -> 106400 | C28: =C25*$B$8 -> 152000 | D28: =D25*$B$8 -> 197600
A29: ROI (%) | B29: =IFERROR((B28*$B$10-$B$5)/$B$5,0) -> -0.50346667 | C29: =IFERROR((C28*$B$10-$B$5)/$B$5,0) -> -0.29066667 | D29: =IFERROR((D28*$B$10-$B$5)/$B$5,0) -> -0.077866667
A31: Break-Even Customers = Marketing Cost ÷ Contribution Margin Per Customer (see row 16). This measures break-even within the 30-day window; profitability over the full customer lifespan is captured by the LTV:CAC ratio instead.
A34: Recommendation
A35: Even in the Conservative scenario, the LTV:CAC ratio remains well above the commonly cited 3:1 SaaS benchmark, suggesting the acquisition assumptions used here have room to absorb higher real-world CAC once live campaign data replaces these planning figures. Priority should go to improving top-of-funnel CTR (the largest drop-off identified in the Funnel Forecast sheet) and validating the churn and conversion-rate assumptions with real customer data as soon as it becomes available.

Sheet Calculation Notes
A1: CALCULATION NOTES
A2: Formulas and definitions used throughout this workbook
A4: Term | B4: Definition / Formula
A5: CTR (Click-Through Rate) | B5: Clicks ÷ Impressions. Measures what share of an audience that saw an ad or post clicked through.
A6: CPC (Cost Per Click) | B6: Channel Budget ÷ Clicks. Average cost paid for each click.
A7: CPL (Cost Per Lead) | B7: Channel Budget ÷ Leads. Average cost to generate one lead.
A8: CAC (Customer Acquisition Cost) | B8: Total Marketing Cost ÷ Number of New Customers. The blended cost to acquire one paying customer.
A9: Conversion Rate | B9: The percentage of prospects that move from one funnel stage to the next (e.g. Leads ÷ Clicks).
A10: Customer Lifespan | B10: 1 ÷ Monthly Churn Rate. The average number of months a customer stays subscribed.
A11: LTV (Customer Lifetime Value) | B11: Monthly Revenue Per Customer × Customer Lifespan × Gross Margin. The total gross profit expected from one customer over their lifetime.
A12: LTV:CAC Ratio | B12: LTV ÷ CAC. A common SaaS health metric; 3:1 or higher is generally considered healthy.
A13: Revenue | B13: Customers × Monthly Revenue Per Customer.
A14: Gross Profit | B14: Revenue × Gross Margin.
A15: ROI (Return on Investment) | B15: (Gross Profit − Marketing Cost) ÷ Marketing Cost × 100.
A16: Break-Even Customers | B16: Marketing Cost ÷ Contribution Margin Per Customer (Monthly Revenue Per Customer × Gross Margin).
A18: Important Notes
A19: • | B19: All figures are hypothetical.
A20: • | B20: No actual campaign data has been provided.
A21: • | B21: Real results may differ.
A22: • | B22: CAC and LTV should be recalculated using real campaign and customer data once available.
A23: • | B23: This model was created for internship learning and planning purposes only.
